MANIFEST.in
setup.cfg
setup.py
tw/__init__.py
tw.timeplot.egg-info/PKG-INFO
tw.timeplot.egg-info/SOURCES.txt
tw.timeplot.egg-info/dependency_links.txt
tw.timeplot.egg-info/entry_points.txt
tw.timeplot.egg-info/namespace_packages.txt
tw.timeplot.egg-info/not-zip-safe
tw.timeplot.egg-info/paster_plugins.txt
tw.timeplot.egg-info/requires.txt
tw.timeplot.egg-info/top_level.txt
tw/timeplot/__init__.py
tw/timeplot/base.py
tw/timeplot/defaults.py
tw/timeplot/release.py
tw/timeplot/samples.py
tw/timeplot/timeplot.py
tw/timeplot/widgets.py
tw/timeplot/static/1.1/timeplot-api.js
tw/timeplot/static/1.1/timeplot-bundle.css
tw/timeplot/static/1.1/timeplot-bundle.js
tw/timeplot/static/1.1/images/copyright.png
tw/timeplot/static/1.1/images/index.html
tw/timeplot/static/1.1/images/index.html?C=M;O=A
tw/timeplot/static/1.1/images/index.html?C=M;O=D
tw/timeplot/static/1.1/images/index.html?C=N;O=A
tw/timeplot/static/1.1/images/index.html?C=N;O=D
tw/timeplot/static/1.1/images/index.html?C=S;O=A
tw/timeplot/static/1.1/images/index.html?C=S;O=D
tw/timeplot/static/1.1/images/line_left.png
tw/timeplot/static/1.1/images/line_right.png
tw/timeplot/static/1.1/images/progress-running.gif
tw/timeplot/static/1.1/lib/excanvas.js
tw/timeplot/static/1.1/lib/index.html
tw/timeplot/static/1.1/lib/index.html?C=M;O=A
tw/timeplot/static/1.1/lib/index.html?C=M;O=D
tw/timeplot/static/1.1/lib/index.html?C=N;O=A
tw/timeplot/static/1.1/lib/index.html?C=N;O=D
tw/timeplot/static/1.1/lib/index.html?C=S;O=A
tw/timeplot/static/1.1/lib/index.html?C=S;O=D
tw/timeplot/static/1.1/lib/firebug/errorIcon.png
tw/timeplot/static/1.1/lib/firebug/firebug.css
tw/timeplot/static/1.1/lib/firebug/firebug.html
tw/timeplot/static/1.1/lib/firebug/firebug.js
tw/timeplot/static/1.1/lib/firebug/firebugx.js
tw/timeplot/static/1.1/lib/firebug/index.html
tw/timeplot/static/1.1/lib/firebug/index.html?C=M;O=A
tw/timeplot/static/1.1/lib/firebug/index.html?C=M;O=D
tw/timeplot/static/1.1/lib/firebug/index.html?C=N;O=A
tw/timeplot/static/1.1/lib/firebug/index.html?C=N;O=D
tw/timeplot/static/1.1/lib/firebug/index.html?C=S;O=A
tw/timeplot/static/1.1/lib/firebug/index.html?C=S;O=D
tw/timeplot/static/1.1/lib/firebug/infoIcon.png
tw/timeplot/static/1.1/lib/firebug/warningIcon.png
tw/timeplot/static/1.1/locales/index.html
